Metadata-Version: 2.2
Name: remove_starfield
Version: 0.0.5
Summary: Python code for estimating and removing a starfield from a set of celestial images
Author: Sam Van Kooten
Requires-Python: >=3.10
License-File: LICENSE
Requires-Dist: astropy>=6.1.2
Requires-Dist: h5py>=3.10
Requires-Dist: ipywidgets>=8.0
Requires-Dist: matplotlib>=3.6
Requires-Dist: numpy>=1.21
Requires-Dist: reproject>=0.13
Requires-Dist: scipy>=1.8
Requires-Dist: tqdm>=4.66
Provides-Extra: test
Requires-Dist: pytest>=8.0; extra == "test"
Requires-Dist: pytest-arraydiff>=0.6; extra == "test"
Requires-Dist: pytest-mock>=3.7; extra == "test"
Requires-Dist: pytest-mpl>=0.16; extra == "test"
Requires-Dist: scipy>=1.15; extra == "test"
